{
  "$type": "/Game/Mods/MapCollectablesMod/Data/PreloadedLocationsDataAssetType",
  "Locations": [
    {
      "x": -1049975,
      "y": -346917,
      "z": 0
    },
    {
      "x": -892000,
      "y": -495104,
      "z": 0
    },
    {
      "x": -835873,
      "y": -9306,
      "z": 0
    },
    {
      "x": -799674,
      "y": -242200,
      "z": 0
    },
    {
      "x": -781076,
      "y": -91020,
      "z": 0
    },
    {
      "x": -766031,
      "y": -416396,
      "z": 0
    },
    {
      "x": -755686,
      "y": -33184,
      "z": 0
    },
    {
      "x": -744527,
      "y": -18492,
      "z": 0
    },
    {
      "x": -718127,
      "y": -96581,
      "z": 0
    },
    {
      "x": -660664,
      "y": -286253,
      "z": 0
    },
    {
      "x": -595484,
      "y": -488487,
      "z": 0
    },
    {
      "x": -570460,
      "y": 123400,
      "z": 0
    },
    {
      "x": -569540,
      "y": 106460,
      "z": 0
    },
    {
      "x": -558251,
      "y": -616871,
      "z": 0
    },
    {
      "x": -551626,
      "y": -148709,
      "z": 0
    },
    {
      "x": -546741,
      "y": -288300,
      "z": 0
    },
    {
      "x": -508860,
      "y": -41200,
      "z": 0
    },
    {
      "x": -501920,
      "y": -41700,
      "z": 0
    },
    {
      "x": -448559,
      "y": 337255,
      "z": 0
    },
    {
      "x": -410395,
      "y": -96703,
      "z": 0
    },
    {
      "x": -404782,
      "y": -444933,
      "z": 0
    },
    {
      "x": -361622,
      "y": 69232,
      "z": 0
    },
    {
      "x": -342042,
      "y": 346794,
      "z": 0
    },
    {
      "x": -331352,
      "y": 251148,
      "z": 0
    },
    {
      "x": -324220,
      "y": 347320,
      "z": 0
    },
    {
      "x": -309227,
      "y": 72251,
      "z": 0
    },
    {
      "x": -269151,
      "y": 324099,
      "z": 0
    },
    {
      "x": -243049,
      "y": -128179,
      "z": 0
    },
    {
      "x": -225720,
      "y": -253070,
      "z": 0
    },
    {
      "x": -219520,
      "y": -265430,
      "z": 0
    },
    {
      "x": -217276,
      "y": 45632,
      "z": 0
    },
    {
      "x": -205300,
      "y": 453400,
      "z": 0
    },
    {
      "x": -192220,
      "y": 444960,
      "z": 0
    },
    {
      "x": -167975,
      "y": 573278,
      "z": 0
    },
    {
      "x": -165099,
      "y": 155823,
      "z": 0
    },
    {
      "x": -146655,
      "y": 181435,
      "z": 0
    },
    {
      "x": -141964,
      "y": 311323,
      "z": 0
    },
    {
      "x": -139111,
      "y": -50039,
      "z": 0
    },
    {
      "x": -135019,
      "y": 225125,
      "z": 0
    },
    {
      "x": -61457,
      "y": -259507,
      "z": 0
    },
    {
      "x": -48988,
      "y": -105792,
      "z": 0
    },
    {
      "x": -39439,
      "y": -155135,
      "z": 0
    },
    {
      "x": -37010,
      "y": 555630,
      "z": 0
    },
    {
      "x": -33390,
      "y": 576770,
      "z": 0
    },
    {
      "x": -19813,
      "y": -53836,
      "z": 0
    },
    {
      "x": -7393,
      "y": 291162,
      "z": 0
    },
    {
      "x": 18483,
      "y": -116758,
      "z": 0
    },
    {
      "x": 73162,
      "y": 241800,
      "z": 0
    },
    {
      "x": 92287,
      "y": 528352,
      "z": 0
    },
    {
      "x": 98366,
      "y": 308512,
      "z": 0
    },
    {
      "x": 143301,
      "y": 89052,
      "z": 0
    },
    {
      "x": 174730,
      "y": 217780,
      "z": 0
    },
    {
      "x": 195700,
      "y": 231510,
      "z": 0
    },
    {
      "x": 484368,
      "y": -664339,
      "z": 0
    },
    {
      "x": 498427,
      "y": -582697,
      "z": 0
    },
    {
      "x": 499030,
      "y": -745574,
      "z": 0
    },
    {
      "x": 499248,
      "y": -730343,
      "z": 0
    },
    {
      "x": 534349,
      "y": -621029,
      "z": 0
    },
    {
      "x": 551098,
      "y": -670142,
      "z": 0
    },
    {
      "x": 572300,
      "y": -697261,
      "z": 0
    },
    {
      "x": 593432,
      "y": -666984,
      "z": 0
    },
    {
      "x": 595206,
      "y": -643495,
      "z": 0
    },
    {
      "x": 608703,
      "y": -679950,
      "z": 0
    },
    {
      "x": 609405,
      "y": -594254,
      "z": 0
    },
    {
      "x": 616621,
      "y": -754349,
      "z": 0
    }
  ]
}